strynova_dj_tailwindcss/__init__.py
strynova_dj_tailwindcss/apps.py
strynova_dj_tailwindcss/bin/README.md
strynova_dj_tailwindcss/bin/tailwindcss
strynova_dj_tailwindcss/bin/tailwindcss.exe
strynova_dj_tailwindcss/management/__init__.py
strynova_dj_tailwindcss/management/__pycache__/__init__.cpython-312.pyc
strynova_dj_tailwindcss/management/commands/__init__.py
strynova_dj_tailwindcss/management/commands/tailwind.py
strynova_dj_tailwindcss/management/commands/__pycache__/__init__.cpython-312.pyc
strynova_dj_tailwindcss/management/commands/__pycache__/tailwind.cpython-312.pyc
strynova_dj_tailwindcss/templatetags/__init__.py
strynova_dj_tailwindcss/templatetags/tailwind_tags.py
strynova_dj_tailwindcss/templatetags/__pycache__/__init__.cpython-312.pyc
strynova_dj_tailwindcss/templatetags/__pycache__/tailwind_tags.cpython-312.pyc
strynova_dj_tailwindcss-0.2.dist-info/licenses/LICENSE
tests/__init__.py
tests/manage.py
tests/test_templatetags.py
strynova_dj_tailwindcss-0.2.dist-info/METADATA
strynova_dj_tailwindcss-0.2.dist-info/WHEEL
strynova_dj_tailwindcss-0.2.dist-info/top_level.txt
strynova_dj_tailwindcss-0.2.dist-info/RECORD
